<?xml version= "1.0" encoding="UTF-8"?>
<mods xmlns:xlink="http://www.w3.org/1999/xlink" xmlns:xsi="http://www.w3.org/2001/XMLSchema-instance" xmlns="http://www.loc.gov/mods/v3" version="3.6" xsi:schemaLocation="http://www.loc.gov/mods/v3 http://www.loc.gov/standards/mods/v3/mods-3-6.xsd">
    <identifier displayLabel = "record number" type = "local">
        11211
    </identifier>
    <originInfo>
        <dateCaptured>
            10/26/2000
        </dateCaptured>
        <dateModified>
            03/08/2002
        </dateModified>
    </originInfo>
    <subject>
        <temporal point = "start">
            07/02/1860
        </temporal>
        <temporal point = "end">
            07/02/1860
        </temporal>
    </subject>
    <note type = "poggenburg date">
        2  VII 60
    </note>
    <note type = "journal content">
        Théodore Banville et Marie Daubrun arrivent à Paris de Nice.  Il dînent chez Marie avec la mère et la petite cousine de celle-ci.  Toutes les trois s'appellent Marie et toutes se ressemblent  {1}
    </note>
    <relatedItem type = "references">
        <identifier displayLabel = "bibliographic abbreviation" type = "local">
            Lacroix
        </indentifier>
        <titleInfo>
            <title>
                Théodore de Banville: Une famille pour un poète: Biographie originale, historique et documentaire
            </title>
        </titleInfo>
        <name type = "personal">
            <namePart>
                Lacroix, Raymond
            </namePart>
            <role>
                <roleTerm type = "text">author</roleTerm>
            </role>
        </name>
        <originInfo>
            <place>
                <placeTerm type = "text">Moulins</placeTerm>
            </place>
            <publisher>
                Pottier
            </publisher>
            <dateIssued>
                1990
            </dateIssued>
            <dateCaptured>
                03/07/2002
            </dateCaptured>
            <dateModified>
                03/08/2002
            </dateModified>
        </originInfo>
        <part>
            <extent unit = "pages">
                <start>
                    291
                </start>
                <end>
                    291
                </end>
            </extent>
        </part>
        <genre>
            Book
        </genre>
    </relatedItem>
</mods>