<?xml version= "1.0" encoding="UTF-8"?>
<mods xmlns:xlink="http://www.w3.org/1999/xlink" xmlns:xsi="http://www.w3.org/2001/XMLSchema-instance" xmlns="http://www.loc.gov/mods/v3" version="3.6" xsi:schemaLocation="http://www.loc.gov/mods/v3 http://www.loc.gov/standards/mods/v3/mods-3-6.xsd">
    <identifier displayLabel = "record number" type = "local">
        9854
    </identifier>
    <originInfo>
        <dateCaptured>
            08/16/1999
        </dateCaptured>
        <dateModified>
            03/08/2002
        </dateModified>
    </originInfo>
    <subject>
        <temporal point = "start">
            05/15/1862
        </temporal>
        <temporal point = "end">
            05/15/1862
        </temporal>
    </subject>
    <note type = "poggenburg date">
        15 V 62
    </note>
    <note type = "journal content">
        Le matin, Baudelaire se rend chez Arsène Houssaye.  Il lui demande de lui donner de l'argent en billets de complaisance. Houssaye s'emporte. Ils ont alors une discussion dépassant nettement le cadre limité  des problèmes financiers.   Plus tard, dans la journée,  Baudelaire écrit à Houssaye, qualifiant leur rencontre d'explication "décisive". Houssaye accuse la jeunesse d'ingratitude. Il cite Banville, qui l'accuse d'être un médiocre administrateur de la Comédie Française.  Baudelaire prend la défense de Banville, et affirme que les problèmes de la Comédie Française sont dûs à la struture administrative de ce théâtre.  Ceci est valable pour tous ses administrateurs. De plus, Houssaye est froissé par l'hésitation de Crépet à l'inclure dans son anthologie  poétique.  Baudelaire prétend qu'au début il a lui-même proposé le nom d'Houssaye, Il a été jusqu'à écrire un article sur lui.  Crépet l'a refusé parce qu'il contenait certaines critiques.  Boyer et lui l'ont défendu auprès de Crépet qui n'a rien voulu savoir.  Il a changé d'avis depuis.  Baudelaire prévoit une rupture entre eux {1}.
    </note>
    <relatedItem type = "references">
        <identifier displayLabel = "bibliographic abbreviation" type = "local">
            JI
        </indentifier>
        <titleInfo>
            <title>
                Journaux intimes. Fusées. Mon Coeur mis à nu. Carnet
            </title>
        </titleInfo>
        <name type = "personal">
            <namePart>
                Baudelaire, Charles
            </namePart>
            <role>
                <roleTerm type = "text">author</roleTerm>
            </role>
        </name>
        <name type = "personal">
            <namePart>
                Crépet, Jacques
            </namePart>
            <role>
                <roleTerm type = "text">editor</roleTerm>
            </role>
        </name>
        <name type = "personal">
            <namePart>
                Blin, Georges
            </namePart>
            <role>
                <roleTerm type = "text">editor</roleTerm>
            </role>
        </name>
        <name type = "personal">
            <namePart>
                Blin, Georges
            </namePart>
            <role>
                <roleTerm type = "text">editor</roleTerm>
            </role>
        </name>
        <originInfo>
            <place>
                <placeTerm type = "text">Paris</placeTerm>
            </place>
            <publisher>
                Librairie José Corti
            </publisher>
            <dateIssued>
                1949
            </dateIssued>
            <dateCaptured>
                03/07/2002
            </dateCaptured>
            <dateModified>
                03/08/2002
            </dateModified>
        </originInfo>
        <part>
            <extent unit = "pages">
                <start>
                    120
                </start>
                <end>
                    120
                </end>
            </extent>
        </part>
        <genre>
            Book
        </genre>
    </relatedItem>
</mods>